keycloak_fastapi/__init__.py
keycloak_fastapi/config/__init__.py
keycloak_fastapi/config/config_provider.py
keycloak_fastapi/groups_permissions.py
keycloak_fastapi/keycloak.py
keycloak_fastapi/models.py
keycloak_fastapi/security.py
keycloak_fastapi/services/__init__.py
keycloak_fastapi/services/client_repository.py
keycloak_fastapi/services/permission_repository.py
keycloak_fastapi/services/realm_repository.py
keycloak_fastapi/services/role_repository.py
keycloak_fastapi/services/user_repository.py
keycloak_fastapi/tools.py
keycloak_fastapi-0.0.1.dist-info/LICENSE
keycloak_fastapi-0.0.1.dist-info/METADATA
keycloak_fastapi-0.0.1.dist-info/WHEEL
keycloak_fastapi-0.0.1.dist-info/RECORD
