Metadata-Version: 2.3
Name: keycloak-fastapi
Version: 0.0.1
Summary: keycloak-fastapi is Python package providing access to custom apps
Keywords: keycloak,openid,oidc
Author: David Campos
Author-email: dcampos@istmocenter.com
Requires-Python: >=3.7,<4.0
Classifier: Development Status :: 3 - Alpha
Classifier: License :: OSI Approved :: MIT License
Classifier: Operating System :: MacOS
Classifier: Operating System :: Microsoft :: Windows
Classifier: Operating System :: Unix
Classifier: Programming Language :: Python :: 3
Classifier: Programming Language :: Python :: 3.7
Classifier: Programming Language :: Python :: 3.8
Classifier: Programming Language :: Python :: 3.9
Classifier: Programming Language :: Python :: 3.10
Classifier: Programming Language :: Python :: 3.11
Classifier: Programming Language :: Python :: 3.12
Classifier: Programming Language :: Python :: 3.13
Classifier: Topic :: Utilities
Requires-Dist: fastapi
Requires-Dist: fastapi-permissions
Requires-Dist: fastapi-security
Requires-Dist: python-keycloak (>=2.16.1,<3.0.0)
